qtpip/__init__.py
qtpip/__main__.py
qtpip/qtpip
qtpip/tool.py
qtpip-0.1.4.dist-info/LicenseRef-Qt-Commercial.txt
qtpip-0.1.4.dist-info/METADATA
qtpip-0.1.4.dist-info/WHEEL
qtpip-0.1.4.dist-info/entry_points.txt
qtpip-0.1.4.dist-info/top_level.txt
qtpip-0.1.4.dist-info/RECORD
