Metadata-Version: 2.1
Name: qtpip
Version: 0.1.4
Summary: A pip wrapper to install Qt for Python commercial wheels
Author-email: Qt for Python Team <pyside@qt-project.org>
License: Qt Commercial
Keywords: qt,pyside,shiboken
Classifier: Programming Language :: Python :: 3
Requires-Python: >=3.7
License-File: LICENSES/LicenseRef-Qt-Commercial.txt
